pyvisq/__init__.py
pyvisq/models/__init__.py
pyvisq/models/burgers.py
pyvisq/models/elements.py
pyvisq/models/generalized.py
pyvisq/models/kelvinvoigt.py
pyvisq/models/maxwell.py
pyvisq/models/model.py
pyvisq/models/powerlaw.py
pyvisq/models/poynting_thomson.py
pyvisq/models/zener.py
pyvisq/utils/__init__.py
pyvisq/utils/hierarchy.py
pyvisq/utils/mittag_leffler.py
pyvisq-1.2.2.dist-info/METADATA
pyvisq-1.2.2.dist-info/WHEEL
pyvisq-1.2.2.dist-info/licenses/LICENSE
pyvisq-1.2.2.dist-info/RECORD
