Metadata-Version: 2.4
Name: pyvisq
Version: 1.2.2
Summary: An open-source package to model/visualize viscoelastic responses.
Project-URL: repository, https://github.com/HoseynAAmiri/pyvisq
License-File: LICENSE
Requires-Python: >=3.11
Requires-Dist: mpmath>=1.3.0
Requires-Dist: pymittagleffler>=0.1.3
Requires-Dist: scipy>=1.15.1
